Metadata-Version: 2.1
Name: yelp-review-scraper
Version: 1.0.0
Summary: A python library to scrape on yelp
Home-page: UNKNOWN
Author: DataKund
Author-email: datakund@gmail.com
License: Apache License 2.0
Keywords: yelp scraper product python bot_studio automation search address review date
Platform: UNKNOWN
License-File: LICENSE
